notebook_copilot/__init__.py
notebook_copilot/agents.py
notebook_copilot/chains.py
notebook_copilot/context.py
notebook_copilot/handlers.py
notebook_copilot/models.py
notebook_copilot/notebook_copilot.py
notebook_copilot/output.py
notebook_copilot/parsers.py
notebook_copilot/prompts.py
notebook_copilot/tools.py
notebook_copilot/utils.py
tests/__init__.py
tests/test_copilot.py
notebook_copilot-0.2.0.dist-info/LICENSE
notebook_copilot-0.2.0.dist-info/METADATA
notebook_copilot-0.2.0.dist-info/WHEEL
notebook_copilot-0.2.0.dist-info/top_level.txt
notebook_copilot-0.2.0.dist-info/RECORD
