Metadata-Version: 2.1
Name: notebook-copilot
Version: 0.2.0
Summary: The Bridge from Thoughts to Well-Crafted Jupyter Notebook
Home-page: https://github.com/talperetz/notebook_copilot
Author: Tal Peretz
Author-email: tp@aihumanlabs.com
License: MIT
Classifier: Development Status :: 3 - Alpha
Classifier: Intended Audience :: Science/Research
Classifier: Intended Audience :: Developers
Classifier: Topic :: Software Development :: Libraries :: Python Modules
Classifier: Topic :: Scientific/Engineering :: Artificial Intelligence
Classifier: Topic :: Scientific/Engineering :: Information Analysis
Classifier: License :: OSI Approved :: MIT License
Classifier: Programming Language :: Python :: 3
Classifier: Programming Language :: Python :: 3.7
Classifier: Programming Language :: Python :: 3.8
Classifier: Programming Language :: Python :: 3.9
Classifier: Programming Language :: Python :: 3.10
Classifier: Operating System :: OS Independent
Classifier: Framework :: Jupyter
Classifier: Natural Language :: English
Requires-Python: >=3.7.1, <4
License-File: LICENSE
Requires-Dist: setuptools (~=65.5.1)
Requires-Dist: ipython (~=8.13.2)
Requires-Dist: langchain (~=0.0.187)
Requires-Dist: pandas (~=2.0.2)
Requires-Dist: pydantic (~=1.10.8)
Requires-Dist: tiktoken (~=0.4.0)
Requires-Dist: ipywidgets (==8.0.6)
Requires-Dist: faiss-cpu (~=1.7.4)
